appsync_schema_uploader/__init__.py
appsync_schema_uploader/__main__.py
appsync_schema_uploader-0.0.4.dist-info/LICENSE
appsync_schema_uploader-0.0.4.dist-info/METADATA
appsync_schema_uploader-0.0.4.dist-info/WHEEL
appsync_schema_uploader-0.0.4.dist-info/top_level.txt
appsync_schema_uploader-0.0.4.dist-info/RECORD
